<!-- 
  dmsetup message /dev/mapper/volg-volg--thinpool-tpool 0 reserve_metadata_snap
  thin_delta  -m --snap1 $(lvs --noheadings -o thin_id volg/thin_volume_snap4) --snap2 $(lvs --noheadings -o thin_id volg/thin_volume_snap5) /dev/mapper/volg-volg--thinpool_tmeta  
  dmsetup message /dev/mapper/volg-volg--thinpool-tpool 0 release_metadata_snap
-->
<superblock uuid="" time="5" transaction="8" data_block_size="128" nr_data_blocks="0">
  <diff left="5" right="6">
    <different begin="0" length="1"/>
    <same begin="1" length="47"/>
    <different begin="48" length="1"/>
    <same begin="49" length="1"/>
    <different begin="50" length="1"/>
    <same begin="51" length="36"/>
    <different begin="87" length="10"/>
    <same begin="97" length="1"/>
    <different begin="98" length="11"/>
    <same begin="109" length="2"/>
    <different begin="111" length="3"/>
    <same begin="114" length="1"/>
    <different begin="115" length="14"/>
    <same begin="129" length="1"/>
    <different begin="130" length="13"/>
    <same begin="143" length="1"/>
    <different begin="144" length="7"/>
    <same begin="151" length="1"/>
    <different begin="152" length="1"/>
    <same begin="153" length="728"/>
    <same begin="2048" length="1"/>
    <same begin="2096" length="4049"/>
    <same begin="6192" length="4049"/>
    <same begin="10288" length="4049"/>
    <same begin="14384" length="4049"/>
    <same begin="18480" length="395"/>
    <different begin="18875" length="1"/>
    <right_only begin="18876" length="37"/>
    <right_only begin="18944" length="330"/>
    <different begin="32768" length="4"/>
    <same begin="32772" length="2"/>
    <different begin="32774" length="1"/>
    <same begin="32775" length="1"/>
    <different begin="32776" length="1"/>
    <same begin="32777" length="2"/>
    <different begin="32779" length="1"/>
    <same begin="32780" length="1"/>
    <different begin="32781" length="20"/>
    <same begin="32801" length="1"/>
    <different begin="32802" length="11"/>
    <same begin="32813" length="1"/>
    <different begin="32814" length="3"/>
    <same begin="32817" length="2"/>
    <different begin="32819" length="1"/>
    <same begin="32820" length="1"/>
    <different begin="32821" length="4"/>
    <same begin="32825" length="1"/>
    <different begin="32826" length="5"/>
    <same begin="32831" length="3"/>
    <different begin="32834" length="1"/>
    <same begin="32835" length="3"/>
    <different begin="32838" length="1"/>
    <same begin="32839" length="2"/>
    <different begin="32841" length="1"/>
    <same begin="32842" length="1"/>
    <different begin="32843" length="1"/>
    <same begin="32844" length="2"/>
    <different begin="32846" length="8"/>
    <same begin="32854" length="3"/>
    <different begin="32857" length="12"/>
    <same begin="32869" length="1"/>
    <different begin="32870" length="1"/>
    <same begin="32871" length="1"/>
    <different begin="32872" length="1"/>
    <same begin="32873" length="1"/>
    <different begin="32874" length="1"/>
    <same begin="32875" length="1"/>
    <different begin="32876" length="1"/>
    <same begin="32877" length="1"/>
    <different begin="32878" length="1"/>
    <same begin="32879" length="1"/>
    <different begin="32880" length="1"/>
    <same begin="32881" length="1"/>
    <different begin="32882" length="5"/>
    <same begin="32887" length="395"/>
    <different begin="33282" length="1"/>
    <same begin="33283" length="292"/>
    <different begin="33575" length="1"/>
    <different begin="34816" length="101"/>
    <same begin="34917" length="8134"/>
    <different begin="43051" length="1"/>
    <right_only begin="43052" length="577"/>
    <right_only begin="44032" length="512"/>
    <same begin="51200" length="1"/>
    <same begin="55296" length="1"/>
    <same begin="65536" length="9"/>
    <different begin="65545" length="10"/>
    <same begin="65555" length="3"/>
    <different begin="65558" length="4"/>
    <same begin="65562" length="7"/>
    <different begin="65569" length="3"/>
    <same begin="65572" length="3"/>
    <different begin="65575" length="2"/>
    <same begin="65577" length="1"/>
    <different begin="65578" length="2"/>
    <same begin="65580" length="8"/>
    <different begin="65588" length="4"/>
    <same begin="65592" length="3"/>
    <different begin="65595" length="14"/>
    <same begin="65609" length="1"/>
    <different begin="65610" length="6"/>
    <same begin="65616" length="1"/>
    <different begin="65617" length="2"/>
    <same begin="65619" length="2"/>
    <different begin="65621" length="1"/>
    <same begin="65622" length="4"/>
    <different begin="65626" length="5"/>
    <same begin="65631" length="1"/>
    <different begin="65632" length="4"/>
    <same begin="65636" length="1"/>
    <different begin="65637" length="3"/>
    <same begin="65640" length="1"/>
    <different begin="65641" length="16"/>
    <same begin="65657" length="1"/>
    <different begin="65658" length="1"/>
    <same begin="65659" length="4"/>
    <different begin="65663" length="1"/>
    <same begin="65664" length="1"/>
    <different begin="65665" length="3"/>
    <same begin="65668" length="1"/>
    <different begin="65669" length="5"/>
    <same begin="65674" length="1"/>
    <different begin="65675" length="8"/>
    <same begin="65683" length="2"/>
    <different begin="65685" length="10"/>
    <same begin="65695" length="1"/>
    <different begin="65696" length="4"/>
    <same begin="65700" length="726"/>
    <same begin="67584" length="4011"/>
    <same begin="98303" length="1"/>
  </diff>
</superblock>
